<?xml version="1.0" encoding="utf-8"?>
<!DOCTYPE hibernate-mapping PUBLIC "-//Hibernate/Hibernate Mapping DTD 3.0//EN"
"http://hibernate.sourceforge.net/hibernate-mapping-3.0.dtd">
<!-- 
    Mapping file autogenerated by MyEclipse Persistence Tools
-->
<hibernate-mapping>
    <class name="cn.edu.entity.TbAdmin" table="tb_admin" catalog="db_graduate">
        <id name="adminNum" type="java.lang.Integer">
            <column name="adminNum" />
            <generator class="native"></generator>
        </id>
        <property name="adminId" type="java.lang.String">
            <column name="adminId" length="10" />
        </property>
        <property name="adminPwd" type="java.lang.String">
            <column name="adminPwd" length="10" />
        </property>
    </class>
</hibernate-mapping>
